alphabit/__init__.py
alphabit/core.py
alphabit-0.1.2.dist-info/METADATA
alphabit-0.1.2.dist-info/WHEEL
alphabit-0.1.2.dist-info/top_level.txt
alphabit-0.1.2.dist-info/RECORD
