Metadata-Version: 2.1
Name: alphabit
Version: 0.1.2
Summary: Hardware-accelerated symbolic stream processing
Home-page: https://github.com/monemax/alphabit
Author: Moneshwaran K.M
Author-email: mone9732@gmail.com
License: UNKNOWN
Platform: UNKNOWN
Classifier: Development Status :: 3 - Alpha
Classifier: Intended Audience :: Developers
Classifier: Intended Audience :: Science/Research
Classifier: License :: OSI Approved :: MIT License
Classifier: Operating System :: OS Independent
Classifier: Programming Language :: Python :: 3
Classifier: Programming Language :: Python :: 3.7
Classifier: Programming Language :: Python :: 3.8
Classifier: Programming Language :: Python :: 3.9
Classifier: Programming Language :: Python :: 3.10
Classifier: Topic :: Scientific/Engineering :: Artificial Intelligence
Classifier: Topic :: System :: Hardware
Requires-Python: >=3.7
Requires-Dist: numpy (>=1.19.0)
Requires-Dist: regex (>=2021.0)
Provides-Extra: dev
Requires-Dist: black ; extra == 'dev'
Requires-Dist: flake8 ; extra == 'dev'
Requires-Dist: pytest-benchmark ; extra == 'dev'
Requires-Dist: pytest (>=6.0) ; extra == 'dev'
